README.rst
setup.cfg
setup.py
hiisi/__init__.py
hiisi/hiisi.py
hiisi/odim.py
hiisi.egg-info/PKG-INFO
hiisi.egg-info/SOURCES.txt
hiisi.egg-info/dependency_links.txt
hiisi.egg-info/top_level.txt