Metadata-Version: 1.1
Name: hiisi
Version: 0.0.9
Summary: Tools for easy handling of hdf5 files
Home-page: https://github.com/karjaljo/hiisi
Author: Joonas Karjalainen
Author-email: joonas.karjalainen@fmi.fi
License: MIT
Keywords: hdf5 hdf hiisi weather radar odim
Platform: UNKNOWN
Classifier: Development Status :: 2 - Pre-Alpha
Classifier: Intended Audience :: Developers
Classifier: Topic :: Scientific/Engineering
Classifier: License :: OSI Approved :: MIT License
Classifier: Programming Language :: Python :: 2.7
